tokarip/__init__.py
tokarip-0.0.0.dist-info/METADATA
tokarip-0.0.0.dist-info/WHEEL
tokarip-0.0.0.dist-info/top_level.txt
tokarip-0.0.0.dist-info/RECORD
