Metadata-Version: 2.1
Name: tokarip
Version: 0.0.0
Summary: tokarip
Requires-Python: >=3.9
